.hgignore
.hgtags
CHANGES.txt
COPYRIGHT.txt
HACKING.txt
LICENSE.txt
bootstrap.py
buildout.cfg
setup.py
src/gocept/__init__.py
src/gocept.autocomplete.egg-info/PKG-INFO
src/gocept.autocomplete.egg-info/SOURCES.txt
src/gocept.autocomplete.egg-info/dependency_links.txt
src/gocept.autocomplete.egg-info/namespace_packages.txt
src/gocept.autocomplete.egg-info/not-zip-safe
src/gocept.autocomplete.egg-info/requires.txt
src/gocept.autocomplete.egg-info/top_level.txt
src/gocept/autocomplete/README.txt
src/gocept/autocomplete/__init__.py
src/gocept/autocomplete/autocomplete_input.pt
src/gocept/autocomplete/configure.zcml
src/gocept/autocomplete/ftesting.zcml
src/gocept/autocomplete/interfaces.py
src/gocept/autocomplete/term.py
src/gocept/autocomplete/testing.py
src/gocept/autocomplete/traversal.py
src/gocept/autocomplete/widget.py
src/gocept/autocomplete/tests/__init__.py
src/gocept/autocomplete/tests/color.py
src/gocept/autocomplete/tests/configure.zcml
src/gocept/autocomplete/tests/layout.pt
src/gocept/autocomplete/tests/test_doctests.py
src/gocept/autocomplete/tests/test_selenium.py
src/gocept/autocomplete/tests/test_widget.py