Metadata-Version: 1.1
Name: gocept.autocomplete
Version: 0.7
Summary: AJAX autocomplete widget for z3c.form
Home-page: https://bitbucket.org/gocept/gocept.autocomplete
Author: gocept
Author-email: mail@gocept.com
License: ZPL 2.1
Platform: UNKNOWN
Classifier: Development Status :: 4 - Beta
Classifier: Framework :: Zope3
Classifier: Intended Audience :: Developers
Classifier: License :: OSI Approved
Classifier: License :: OSI Approved :: Zope Public License
Classifier: Natural Language :: English
Classifier: Operating System :: OS Independent
Classifier: Programming Language :: Python
Classifier: Programming Language :: Python :: 2
Classifier: Programming Language :: Python :: 2.7
Classifier: Programming Language :: Python :: 2 :: Only
Classifier: Programming Language :: Python :: Implementation
Classifier: Programming Language :: Python :: Implementation :: CPython
Classifier: Topic :: Software Development :: Libraries
